srcom/__init__.py
srcom/abcs.py
srcom/client.py
srcom/dataclasses.py
srcom/http.py
srcom/utils.py
srcom.py-0.0.2.dist-info/LICENSE
srcom.py-0.0.2.dist-info/METADATA
srcom.py-0.0.2.dist-info/WHEEL
srcom.py-0.0.2.dist-info/top_level.txt
srcom.py-0.0.2.dist-info/RECORD
