Metadata-Version: 2.1
Name: srcom.py
Version: 0.0.2
Summary: A python wrapper for the speedrun.com API
Home-page: https://github.com/zaxutic/srcom.py
Author: Zaxutic
Author-email: zax@zaxu.xyz
License: MIT
Project-URL: Bug Tracker, https://github.com/zaxutic/srcom.py/issues
Platform: UNKNOWN
Classifier: License :: OSI Approved :: MIT License
Classifier: Intended Audience :: Developers
Classifier: Natural Language :: English
Classifier: Operating System :: OS Independent
Classifier: Programming Language :: Python :: 3
Classifier: Programming Language :: Python :: 3.6
Classifier: Programming Language :: Python :: 3.7
Classifier: Programming Language :: Python :: 3.8
Classifier: Programming Language :: Python :: 3.9
Classifier: Topic :: Internet
Classifier: Topic :: Software Development :: Libraries
Classifier: Topic :: Software Development :: Libraries :: Python Modules
Classifier: Topic :: Utilities
Requires-Python: >=3.6
License-File: LICENSE
